AUTHORS.rst
CONTRIBUTING.rst
HISTORY.rst
LICENSE
MANIFEST.in
README.rst
setup.py
dictregister/__init__.py
dictregister/dictregister.py
dictregister.egg-info/PKG-INFO
dictregister.egg-info/SOURCES.txt
dictregister.egg-info/dependency_links.txt
dictregister.egg-info/not-zip-safe
dictregister.egg-info/top_level.txt