Metadata-Version: 1.1
Name: dictregister
Version: 0.9.0.post1
Summary: A searchable list of dictionaries
Home-page: https://github.com/lgiordani/dictregister
Author: Leonardo Giordani
Author-email: giordani.leonardo@gmail.com
License: BSD
Keywords: dictregister
Platform: UNKNOWN
Classifier: Development Status :: 5 - Production/Stable
Classifier: Intended Audience :: Developers
Classifier: License :: OSI Approved :: BSD License
Classifier: Natural Language :: English
Classifier: Programming Language :: Python :: 2
Classifier: Programming Language :: Python :: 2.6
Classifier: Programming Language :: Python :: 2.7
Classifier: Programming Language :: Python :: 3
Classifier: Programming Language :: Python :: 3.3
